main.py
mseep_paypal_invoice_mcp_server-0.1.4.dist-info/METADATA
mseep_paypal_invoice_mcp_server-0.1.4.dist-info/WHEEL
mseep_paypal_invoice_mcp_server-0.1.4.dist-info/entry_points.txt
mseep_paypal_invoice_mcp_server-0.1.4.dist-info/top_level.txt
mseep_paypal_invoice_mcp_server-0.1.4.dist-info/RECORD
